{
  "type": "compare",
  "slug": "omnisend-vs-loops",
  "title": "Omnisend vs Loops (2025): Which Is Better?",
  "meta_description": "Omnisend vs Loops: compare pricing, features, and real use cases to find the right email tool.",
  "h1": "Omnisend vs Loops: Side-by-Side Comparison (2025)",
  "intro": "Choosing between Omnisend and Loops comes down to your specific use case. Omnisend is built for e-commerce brands wanting email and SMS together, while Loops targets SaaS companies sending product and lifecycle emails.",
  "quick_verdict": {
    "winner_overall": "Loops",
    "winner_price": "Omnisend",
    "winner_features": "Omnisend",
    "winner_beginners": "Omnisend",
    "winner_ecommerce": "Omnisend"
  },
  "comparison_table": [
    {
      "feature": "Starting price",
      "tool_a": "$16/mo",
      "tool_b": "$49/mo"
    },
    {
      "feature": "Free plan",
      "tool_a": "Yes",
      "tool_b": "Yes"
    },
    {
      "feature": "Best for",
      "tool_a": "E-Commerce Brands Wanting Email And Sms Together",
      "tool_b": "Saas Companies Sending Product And Lifecycle Emails"
    },
    {
      "feature": "Free subscriber limit",
      "tool_a": "250",
      "tool_b": "1000"
    },
    {
      "feature": "G2 rating",
      "tool_a": "4.5",
      "tool_b": "4.7"
    }
  ],
  "choose_a_if": [
    "You are primarily focused on e-commerce brands wanting email and SMS together",
    "You value omnichannel automation",
    "You prefer freemium pricing"
  ],
  "choose_b_if": [
    "You are primarily focused on SaaS companies sending product and lifecycle emails",
    "You value transactional email",
    "You prefer freemium pricing"
  ],
  "faq": [
    {
      "q": "Is Omnisend better than Loops?",
      "a": "It depends on your use case. Omnisend wins for e-commerce brands wanting email and SMS together, while Loops is stronger for SaaS companies sending product and lifecycle emails."
    },
    {
      "q": "Which is cheaper, Omnisend or Loops?",
      "a": "Omnisend starts at a lower price point. Pricing scales with subscriber count so total cost depends on your list size."
    },
    {
      "q": "Can I switch from Loops to Omnisend?",
      "a": "Yes, switching is possible. Most platforms support CSV import/export. Plan time to recreate automations and templates."
    }
  ]
}